[
  {
    "q": "Ohm’s law states that current through a conductor is directly proportional to:",
    "opts": [
      "Resistance",
      "Voltage",
      "Power",
      "Temperature only"
    ],
    "ans": 1,
    "exp": "Ohm’s law: V ∝ I, so I ∝ V for constant resistance."
  },
  {
    "q": "The SI unit of electrical resistance is:",
    "opts": [
      "Volt",
      "Ampere",
      "Ohm",
      "Watt"
    ],
    "ans": 2,
    "exp": "Resistance is measured in ohm (Ω)."
  },
  {
    "q": "Two resistors 2 Ω and 3 Ω are connected in series. Equivalent resistance is:",
    "opts": [
      "5 Ω",
      "1.2 Ω",
      "6 Ω",
      "0.5 Ω"
    ],
    "ans": 0,
    "exp": "Series: R_eq = R1 + R2 = 5 Ω."
  },
  {
    "q": "Two resistors 2 Ω and 3 Ω are connected in parallel. Equivalent resistance is:",
    "opts": [
      "5 Ω",
      "1.2 Ω",
      "6 Ω",
      "2.5 Ω"
    ],
    "ans": 1,
    "exp": "1/R = 1/2 + 1/3 = 5/6 ⇒ R = 6/5 = 1.2 Ω."
  },
  {
    "q": "Kirchhoff’s Current Law is based on conservation of:",
    "opts": [
      "Energy",
      "Charge",
      "Momentum",
      "Mass"
    ],
    "ans": 1,
    "exp": "Sum of currents entering a junction equals sum leaving."
  },
  {
    "q": "Kirchhoff’s Voltage Law is based on conservation of:",
    "opts": [
      "Charge",
      "Energy",
      "Mass",
      "Force"
    ],
    "ans": 1,
    "exp": "Sum of potential differences in a loop is zero."
  },
  {
    "q": "In a series circuit, current is:",
    "opts": [
      "Different in each resistor",
      "Same in all components",
      "Zero",
      "Maximum at end"
    ],
    "ans": 1,
    "exp": "Same current flows through series components."
  },
  {
    "q": "In a parallel circuit, voltage across each branch is:",
    "opts": [
      "Different",
      "Same",
      "Zero",
      "Infinite"
    ],
    "ans": 1,
    "exp": "All branches have same potential difference."
  },
  {
    "q": "A 10 V battery is connected to a 5 Ω resistor. Current is:",
    "opts": [
      "0.5 A",
      "2 A",
      "5 A",
      "10 A"
    ],
    "ans": 1,
    "exp": "I = V/R = 10/5 = 2 A."
  },
  {
    "q": "Electrical power is given by:",
    "opts": [
      "P = VI",
      "P = V/I",
      "P = IR",
      "P = V + I"
    ],
    "ans": 0,
    "exp": "Power = voltage × current."
  },
  {
    "q": "Unit of electrical power is:",
    "opts": [
      "Joule",
      "Watt",
      "Volt",
      "Ohm"
    ],
    "ans": 1,
    "exp": "SI unit of power is watt."
  },
  {
    "q": "If resistance increases, current (for constant voltage):",
    "opts": [
      "Increases",
      "Decreases",
      "Remains same",
      "Becomes infinite"
    ],
    "ans": 1,
    "exp": "I = V/R, so current decreases."
  },
  {
    "q": "A voltmeter is connected in:",
    "opts": [
      "Series",
      "Parallel",
      "Both series and parallel",
      "Not connected"
    ],
    "ans": 1,
    "exp": "Voltmeter measures potential difference across components."
  },
  {
    "q": "An ammeter is connected in:",
    "opts": [
      "Parallel",
      "Series",
      "Both",
      "Open circuit"
    ],
    "ans": 1,
    "exp": "Ammeter measures current in series."
  },
  {
    "q": "Ideal ammeter has resistance:",
    "opts": [
      "Zero",
      "Infinite",
      "Very high",
      "Variable"
    ],
    "ans": 0,
    "exp": "Ideal ammeter does not affect current."
  },
  {
    "q": "Ideal voltmeter has resistance:",
    "opts": [
      "Zero",
      "Infinite",
      "Very low",
      "Negative"
    ],
    "ans": 1,
    "exp": "No current should flow through voltmeter."
  },
  {
    "q": "A wire of length L and resistance R is stretched to double length. New resistance is:",
    "opts": [
      "2R",
      "4R",
      "R/2",
      "R"
    ],
    "ans": 1,
    "exp": "R ∝ L² when volume constant, so R becomes 4R."
  },
  {
    "q": "Conductance is reciprocal of:",
    "opts": [
      "Voltage",
      "Current",
      "Resistance",
      "Power"
    ],
    "ans": 2,
    "exp": "G = 1/R."
  },
  {
    "q": "Unit of conductance is:",
    "opts": [
      "Ohm",
      "Siemens",
      "Volt",
      "Ampere"
    ],
    "ans": 1,
    "exp": "Siemens (S) is unit of conductance."
  },
  {
    "q": "In a series circuit, total resistance is:",
    "opts": [
      "Less than smallest resistor",
      "Greater than largest resistor",
      "Zero",
      "Infinite always"
    ],
    "ans": 1,
    "exp": "Series resistances add up."
  },
  {
    "q": "In parallel combination, equivalent resistance is:",
    "opts": [
      "Greater than largest resistor",
      "Less than smallest resistor",
      "Equal to sum",
      "Infinite"
    ],
    "ans": 1,
    "exp": "Parallel reduces equivalent resistance."
  },
  {
    "q": "Ohm’s law is valid when:",
    "opts": [
      "Temperature is constant",
      "Current is zero",
      "Voltage is zero",
      "Resistance is infinite"
    ],
    "ans": 0,
    "exp": "Ohmic behavior requires constant temperature."
  },
  {
    "q": "A 100 W bulb at 220 V has current approximately:",
    "opts": [
      "0.45 A",
      "2 A",
      "5 A",
      "10 A"
    ],
    "ans": 0,
    "exp": "I = P/V = 100/220 ≈ 0.45 A."
  },
  {
    "q": "Electrical energy consumed is given by:",
    "opts": [
      "E = Pt",
      "E = V/I",
      "E = IR",
      "E = Vt"
    ],
    "ans": 0,
    "exp": "Energy = power × time."
  },
  {
    "q": "A fuse is used to protect:",
    "opts": [
      "Voltage",
      "Current overload",
      "Resistance",
      "Power factor"
    ],
    "ans": 1,
    "exp": "Fuse melts when current exceeds safe limit."
  },
  {
    "q": "Short circuit results in:",
    "opts": [
      "High resistance",
      "Low current",
      "Very high current",
      "No current"
    ],
    "ans": 2,
    "exp": "Resistance becomes nearly zero."
  },
  {
    "q": "In a resistor, V-I graph is:",
    "opts": [
      "Parabolic",
      "Straight line",
      "Circular",
      "Exponential"
    ],
    "ans": 1,
    "exp": "Ohmic conductor gives linear relation."
  },
  {
    "q": "If two equal resistors are in parallel, equivalent resistance is:",
    "opts": [
      "Double R",
      "Half R",
      "Zero",
      "R"
    ],
    "ans": 1,
    "exp": "R_eq = R/2 for equal resistors."
  },
  {
    "q": "Battery emf is defined as:",
    "opts": [
      "Energy per unit charge",
      "Current per unit voltage",
      "Resistance per unit length",
      "Power per unit time"
    ],
    "ans": 0,
    "exp": "EMF = work done per unit charge."
  },
  {
    "q": "Internal resistance of a cell causes:",
    "opts": [
      "Increase in terminal voltage",
      "Decrease in terminal voltage",
      "No change",
      "Infinite current"
    ],
    "ans": 1,
    "exp": "Voltage drops inside the cell."
  },
  {
    "q": "Terminal voltage is maximum when:",
    "opts": [
      "Current is maximum",
      "Current is zero",
      "Resistance is zero",
      "Power is maximum"
    ],
    "ans": 1,
    "exp": "V = E when no current flows."
  },
  {
    "q": "Electrical resistance depends on:",
    "opts": [
      "Length and area",
      "Mass only",
      "Voltage only",
      "Current only"
    ],
    "ans": 0,
    "exp": "R = ρL/A."
  },
  {
    "q": "Resistivity depends on:",
    "opts": [
      "Material",
      "Length",
      "Area",
      "Current"
    ],
    "ans": 0,
    "exp": "Resistivity is material property."
  },
  {
    "q": "A superconductor has resistance:",
    "opts": [
      "Very high",
      "Zero",
      "Infinite",
      "Variable"
    ],
    "ans": 1,
    "exp": "Below critical temperature, resistance becomes zero."
  },
  {
    "q": "Power loss in resistor is given by:",
    "opts": [
      "I²R",
      "V²R",
      "IR",
      "V/I"
    ],
    "ans": 0,
    "exp": "Joule heating formula."
  },
  {
    "q": "If voltage doubles, power (constant R) becomes:",
    "opts": [
      "Double",
      "Half",
      "Four times",
      "Same"
    ],
    "ans": 2,
    "exp": "P = V²/R."
  },
  {
    "q": "In series combination, voltage divides based on:",
    "opts": [
      "Resistance",
      "Current",
      "Power",
      "Charge"
    ],
    "ans": 0,
    "exp": "Higher resistance gets more voltage drop."
  },
  {
    "q": "Equivalent resistance of infinite series resistors is:",
    "opts": [
      "Zero",
      "Infinite",
      "Finite",
      "Negative"
    ],
    "ans": 1,
    "exp": "Sum diverges."
  },
  {
    "q": "Which device converts electrical energy to heat?",
    "opts": [
      "Motor",
      "Heater",
      "Generator",
      "Transformer"
    ],
    "ans": 1,
    "exp": "Heaters use Joule heating effect."
  },
  {
    "q": "If current doubles, heat produced in resistor becomes:",
    "opts": [
      "Double",
      "Half",
      "Four times",
      "Same"
    ],
    "ans": 2,
    "exp": "H ∝ I²."
  },
  {
    "q": "Kirchhoff’s laws are valid for:",
    "opts": [
      "AC circuits only",
      "DC circuits only",
      "Both AC and DC circuits",
      "Only resistors"
    ],
    "ans": 2,
    "exp": "They are general conservation laws."
  },
  {
    "q": "Node in circuit means:",
    "opts": [
      "Closed loop",
      "Point where branches meet",
      "Battery terminal",
      "Resistor end only"
    ],
    "ans": 1,
    "exp": "Junction of two or more elements."
  },
  {
    "q": "Loop in circuit is:",
    "opts": [
      "Open path",
      "Closed conducting path",
      "Broken wire",
      "Single resistor"
    ],
    "ans": 1,
    "exp": "Loop is a closed circuit path."
  },
  {
    "q": "In ideal wire, resistance is:",
    "opts": [
      "Infinite",
      "Zero",
      "Very high",
      "Variable"
    ],
    "ans": 1,
    "exp": "No energy loss in ideal wire."
  },
  {
    "q": "Electric current is defined as:",
    "opts": [
      "Charge per unit time",
      "Energy per unit charge",
      "Power per unit time",
      "Force per unit charge"
    ],
    "ans": 0,
    "exp": "I = Q/t."
  },
  {
    "q": "If resistance increases in a fixed circuit, current:",
    "opts": [
      "Increases",
      "Decreases",
      "Remains same",
      "Becomes infinite"
    ],
    "ans": 1,
    "exp": "Ohm’s law: I = V/R."
  }
]
